web3_mcp/__init__.py
web3_mcp/__main__.py
web3_mcp/__version__.py
web3_mcp/auth.py
web3_mcp/constants.py
web3_mcp/py.typed
web3_mcp/server.py
web3_mcp/api/__init__.py
web3_mcp/api/nft.py
web3_mcp/api/query.py
web3_mcp/api/token.py
web3_mcp-0.1.5.dist-info/METADATA
web3_mcp-0.1.5.dist-info/WHEEL
web3_mcp-0.1.5.dist-info/entry_points.txt
web3_mcp-0.1.5.dist-info/RECORD
