Metadata-Version: 2.4
Name: web3-mcp
Version: 0.1.5
Summary: FastMCP server wrapping Ankr Advanced API
Requires-Python: >=3.12
Requires-Dist: ankr-sdk>=1.0.2
Requires-Dist: fastmcp>=2.2.0
Provides-Extra: dev
Requires-Dist: black>=25.1.0; extra == 'dev'
Requires-Dist: isort>=6.0.1; extra == 'dev'
Requires-Dist: mypy>=1.15.0; extra == 'dev'
Requires-Dist: pre-commit>=4.2.0; extra == 'dev'
Requires-Dist: pytest-asyncio>=0.26.0; extra == 'dev'
Requires-Dist: pytest>=8.3.5; extra == 'dev'
Requires-Dist: ruff>=0.11.5; extra == 'dev'
